pycli_mcp/__init__.py
pycli_mcp/__main__.py
pycli_mcp/cli.py
pycli_mcp/py.typed
pycli_mcp/server.py
pycli_mcp/metadata/__init__.py
pycli_mcp/metadata/interface.py
pycli_mcp/metadata/query.py
pycli_mcp/metadata/types/__init__.py
pycli_mcp/metadata/types/argparse.py
pycli_mcp/metadata/types/click.py
pycli_mcp-0.3.0.dist-info/METADATA
pycli_mcp-0.3.0.dist-info/WHEEL
pycli_mcp-0.3.0.dist-info/entry_points.txt
pycli_mcp-0.3.0.dist-info/licenses/LICENSE.txt
pycli_mcp-0.3.0.dist-info/RECORD
