Metadata-Version: 2.4
Name: pycli-mcp
Version: 0.3.0
Summary: MCP server for any Python command line application
Project-URL: Homepage, https://ofek.dev/pycli-mcp/
Project-URL: Sponsor, https://github.com/sponsors/ofek
Project-URL: Changelog, https://ofek.dev/pycli-mcp/changelog/
Project-URL: Tracker, https://github.com/ofek/pycli-mcp/issues
Project-URL: Source, https://github.com/ofek/pycli-mcp
Author-email: Ofek Lev <oss@ofek.dev>
License-Expression: MIT
License-File: LICENSE.txt
Keywords: ai,cli,click,mcp
Classifier: Development Status :: 4 - Beta
Classifier: Programming Language :: Python
Classifier: Programming Language :: Python :: 3.10
Classifier: Programming Language :: Python :: 3.11
Classifier: Programming Language :: Python :: 3.12
Classifier: Programming Language :: Python :: 3.13
Classifier: Programming Language :: Python :: 3.14
Classifier: Programming Language :: Python :: Implementation :: CPython
Classifier: Programming Language :: Python :: Implementation :: PyPy
Requires-Python: >=3.10
Requires-Dist: click
Requires-Dist: mcp
